bazaar_bundle/__init__.py
bazaar_bundle/bundle.py
bazaar_bundle-0.1.dist-info/DESCRIPTION.rst
bazaar_bundle-0.1.dist-info/METADATA
bazaar_bundle-0.1.dist-info/RECORD
bazaar_bundle-0.1.dist-info/WHEEL
bazaar_bundle-0.1.dist-info/metadata.json
bazaar_bundle-0.1.dist-info/top_level.txt
