Metadata-Version: 2.0
Name: bazaar-bundle
Version: 0.1
Summary: Bazaar support for applauncher
Home-page: https://github.com/applauncher-team/bazaar_bundle
Author: Alvaro Garcia Gomez
Author-email: maxpowel@gmail.com
License: UNKNOWN
Download-URL: https://github.com/applauncher-team/bazaar_bundle/archive/master.zip
Keywords: bazaar,mongo,s3,applauncher
Platform: UNKNOWN
Classifier: Topic :: Adaptive Technologies
Classifier: Topic :: Software Development
Classifier: Topic :: System
Classifier: Topic :: Utilities
Requires-Dist: bazaar
